Workbook
Name aporte: app!$D$23
Name patrimonio: app!$D$26
Name qtd_anos: app!$D$24
Name rendimento_carteira: app!$D$17
Name salario: app!$D$16
Name sugestao_investimento: app!$D$18
Name taxa_mensal: app!$D$25

Sheet app
B15: configurações
B16: salario | D16: 4200
B17: rendimento carteira | D17: 0.006
B18: sugestao de investimento | D18: =D16*30% -> 1260
B22: investimento mensal
B23: Quanto investir por mês ? | D23: 500
B24: Por Quantos Anos ? | D24: 5
B25: Taxa de Rendimento mensal ? | D25: 0.01079
B26: Patrimônio acumulado ? | D26: =FV(taxa_mensal,qtd_anos*12,-aporte) -> 41888.457
B27: Dividendos Mensais ? | D27: =patrimonio*rendimento_carteira -> 251.33074
B30: cenários | D30: dividendo
B31: quanto eu teria em 2 anos? | C31: 13613.814 | D31: =C31*rendimento_carteira -> 81.682882
B32: quanto em 5 anos? | C32: 41888.457 | D32: =C32*rendimento_carteira -> 251.33074
B33: quanto em 10 anos? | C33: 121642.11 | D33: =C33*rendimento_carteira -> 729.85264
B34: quanto em 20 anos? | C34: 562599.2 | D34: =C34*rendimento_carteira -> 3375.5952
B35: quanto em 30 anos? | C35: 2161084.8 | D35: =C35*rendimento_carteira -> 12966.509
B38: perfil | C38: Conservador
B39: VALOR A SER INVESTIDO POR MÊS | C39: =aporte -> 500
B42: TIPO DE FII | C42: Percentual sugerido | D42: Valores
B43: PAPEL | C43: =VLOOKUP($C$38&"-"&B43,percentuais!$A$3:$D$20,4,0) -> 0.3 | D43: =C43*$C$39 -> 150
B44: TIJOLO | C44: =VLOOKUP($C$38&"-"&B44,percentuais!$A$3:$D$20,4,0) -> 0.5 | D44: =C44*$C$39 -> 250
B45: HÍBRIDOS | C45: =VLOOKUP($C$38&"-"&B45,percentuais!$A$3:$D$20,4,0) -> 0.1 | D45: =C45*$C$39 -> 50
B46: FOF | C46: =VLOOKUP($C$38&"-"&B46,percentuais!$A$3:$D$20,4,0) -> 0.1 | D46: =C46*$C$39 -> 50
B47: DESENVOLVIMENTO | C47: =VLOOKUP($C$38&"-"&B47,percentuais!$A$3:$D$20,4,0) -> 0 | D47: =C47*$C$39 -> 0
B48: HOTELARIAS | C48: =VLOOKUP($C$38&"-"&B48,percentuais!$A$3:$D$20,4,0) -> 0 | D48: =C48*$C$39 -> 0
B49: TOTAL | D49: =SUM(D43:D48) -> 500

Sheet percentuais
A2: chave | B2: perfil | C2: tipo de FII | D2: percentual
A3: =B3&"-"&C3 -> Conservador-PAPEL | B3: Conservador | C3: PAPEL | D3: 0.3
A4: =B4&"-"&C4 -> Conservador-TIJOLO | B4: Conservador | C4: TIJOLO | D4: 0.5
A5: =B5&"-"&C5 -> Conservador-HÍBRIDOS | B5: Conservador | C5: HÍBRIDOS | D5: 0.1
A6: =B6&"-"&C6 -> Conservador-FOF | B6: Conservador | C6: FOF | D6: 0.1
A7: =B7&"-"&C7 -> Conservador-DESENVOLVIMENTO | B7: Conservador | C7: DESENVOLVIMENTO | D7: 0
A8: =B8&"-"&C8 -> Conservador-HOTELARIAS | B8: Conservador | C8: HOTELARIAS | D8: 0
A9: =B9&"-"&C9 -> Moderado-PAPEL | B9: Moderado | C9: PAPEL | D9: 0.22
A10: =B10&"-"&C10 -> Moderado-TIJOLO | B10: Moderado | C10: TIJOLO | D10: 0.4
A11: =B11&"-"&C11 -> Moderado-HÍBRIDOS | B11: Moderado | C11: HÍBRIDOS | D11: 0.08
A12: =B12&"-"&C12 -> Moderado-FOF | B12: Moderado | C12: FOF | D12: 0.1
A13: =B13&"-"&C13 -> Moderado-DESENVOLVIMENTO | B13: Moderado | C13: DESENVOLVIMENTO | D13: 0.1
A14: =B14&"-"&C14 -> Moderado-HOTELARIAS | B14: Moderado | C14: HOTELARIAS | D14: 0.1
... A20: =B20&"-"&C20 -> Agressivo-HOTELARIAS | B20: Agressivo | C20: HOTELARIAS | D20: 0.1
